odoo/addons/rma_sale_delivery/README.rst
odoo/addons/rma_sale_delivery/__init__.py
odoo/addons/rma_sale_delivery/__manifest__.py
odoo/addons/rma_sale_delivery/i18n/es.po
odoo/addons/rma_sale_delivery/i18n/it.po
odoo/addons/rma_sale_delivery/i18n/rma_sale_delivery.pot
odoo/addons/rma_sale_delivery/readme/CONTRIBUTORS.md
odoo/addons/rma_sale_delivery/readme/DESCRIPTION.md
odoo/addons/rma_sale_delivery/static/description/icon.png
odoo/addons/rma_sale_delivery/static/description/index.html
odoo/addons/rma_sale_delivery/tests/__init__.py
odoo/addons/rma_sale_delivery/tests/test_rma_sale_delivery.py
odoo/addons/rma_sale_delivery/wizard/__init__.py
odoo/addons/rma_sale_delivery/wizard/sale_order_rma_wizard.py
odoo/addons/rma_sale_delivery/wizard/sale_order_rma_wizard_views.xml
odoo_addon_rma_sale_delivery-18.0.1.0.0.4.dist-info/METADATA
odoo_addon_rma_sale_delivery-18.0.1.0.0.4.dist-info/WHEEL
odoo_addon_rma_sale_delivery-18.0.1.0.0.4.dist-info/top_level.txt
odoo_addon_rma_sale_delivery-18.0.1.0.0.4.dist-info/RECORD
